<?xml version="1.0" encoding="utf-8"?>
<clothing-items>
 <clothing>
  <id>
   306230721
  </id>
  <name>
   Converse Dress B-5550
  </name>
  <category>
   Dress
  </category>
  <size>
   M
  </size>
  <color>
   Зеленый
  </color>
  <material>
   Полиэстер
  </material>
  <price>
   704004
  </price>
  <rating>
   1.85
  </rating>
  <reviews>
   940567
  </reviews>
  <new>
   -
  </new>
  <exclusive>
   yes
  </exclusive>
  <sporty>
   no
  </sporty>
 </clothing>
 <clothing>
  <id>
   731380589
  </id>
  <name>
   New Balance Jacket W-4609
  </name>
  <category>
   Jacket
  </category>
  <size>
   L
  </size>
  <color>
   Желтый
  </color>
  <material>
   Шелк
  </material>
  <price>
   950789
  </price>
  <rating>
   3.61
  </rating>
  <reviews>
   564982
  </reviews>
  <new>
   -
  </new>
  <exclusive>
   yes
  </exclusive>
  <sporty>
   no
  </sporty>
 </clothing>
 <clothing>
  <id>
   936402979
  </id>
  <name>
   DC Shoes C-3096
  </name>
  <category>
   Shoes
  </category>
  <size>
   L
  </size>
  <color>
   Зеленый
  </color>
  <material>
   Шерсть
  </material>
  <price>
   543341
  </price>
  <rating>
   2.2
  </rating>
  <reviews>
   259721
  </reviews>
  <new>
   +
  </new>
  <exclusive>
   no
  </exclusive>
 </clothing>
 <clothing>
  <id>
   295748475
  </id>
  <name>
   Fila Dress N-9228
  </name>
  <category>
   Dress
  </category>
  <size>
   S
  </size>
  <color>
   Фиолетовый
  </color>
  <material>
   Кожа
  </material>
  <price>
   578574
  </price>
  <rating>
   2.02
  </rating>
  <reviews>
   24963
  </reviews>
  <new>
   +
  </new>
 </clothing>
 <clothing>
  <id>
   169998946
  </id>
  <name>
   Lacoste Gloves A-5520
  </name>
  <category>
   Gloves
  </category>
  <size>
   XXL
  </size>
  <color>
   Красный
  </color>
  <material>
   Кожа
  </material>
  <price>
   709240
  </price>
  <rating>
   3.34
  </rating>
  <reviews>
   19321
  </reviews>
  <new>
   -
  </new>
  <exclusive>
   no
  </exclusive>
 </clothing>
 <clothing>
  <id>
   469692121
  </id>
  <name>
   Puma T-shirt Q-6329
  </name>
  <category>
   T-shirt
  </category>
  <size>
   L
  </size>
  <color>
   Голубой
  </color>
  <material>
   Полиэстер
  </material>
  <price>
   349131
  </price>
  <rating>
   2.09
  </rating>
  <reviews>
   5793
  </reviews>
  <new>
   +
  </new>
 </clothing>
 <clothing>
  <id>
   599703006
  </id>
  <name>
   Converse Shirt E-7529
  </name>
  <category>
   Shirt
  </category>
  <size>
   M
  </size>
  <color>
   Оранжевый
  </color>
  <material>
   Лен
  </material>
  <price>
   281193
  </price>
  <rating>
   3.62
  </rating>
  <reviews>
   350223
  </reviews>
  <sporty>
   no
  </sporty>
 </clothing>
 <clothing>
  <id>
   549699091
  </id>
  <name>
   Brooks Skirt V-8149
  </name>
  <category>
   Skirt
  </category>
  <size>
   S
  </size>
  <color>
   Фиолетовый
  </color>
  <material>
   Шелк
  </material>
  <price>
   632568
  </price>
  <rating>
   2.08
  </rating>
  <reviews>
   754802
  </reviews>
  <new>
   -
  </new>
  <exclusive>
   yes
  </exclusive>
  <sporty>
   no
  </sporty>
 </clothing>
 <clothing>
  <id>
   955925778
  </id>
  <name>
   Converse Hat E-7575
  </name>
  <category>
   Hat
  </category>
  <size>
   S
  </size>
  <color>
   Синий
  </color>
  <material>
   Полиэстер
  </material>
  <price>
   783793
  </price>
  <rating>
   1.78
  </rating>
  <reviews>
   809239
  </reviews>
  <exclusive>
   no
  </exclusive>
 </clothing>
 <clothing>
  <id>
   696201698
  </id>
  <name>
   Under Armour Pants N-9783
  </name>
  <category>
   Pants
  </category>
  <size>
   XL
  </size>
  <color>
   Зеленый
  </color>
  <material>
   Шерсть
  </material>
  <price>
   516181
  </price>
  <rating>
   4.51
  </rating>
  <reviews>
   70904
  </reviews>
  <new>
   -
  </new>
  <exclusive>
   no
  </exclusive>
  <sporty>
   no
  </sporty>
 </clothing>
 <clothing>
  <id>
   392272081
  </id>
  <name>
   Reebok Shirt M-3326
  </name>
  <category>
   Shirt
  </category>
  <size>
   M
  </size>
  <color>
   Красный
  </color>
  <material>
   Лен
  </material>
  <price>
   994619
  </price>
  <rating>
   2.77
  </rating>
  <reviews>
   726845
  </reviews>
 </clothing>
 <clothing>
  <id>
   520921932
  </id>
  <name>
   Ellesse Umbrellas L-1298
  </name>
  <category>
   Umbrellas
  </category>
  <size>
   L
  </size>
  <color>
   Зеленый
  </color>
  <material>
   Кожа
  </material>
  <price>
   489650
  </price>
  <rating>
   1.14
  </rating>
  <reviews>
   904683
  </reviews>
  <sporty>
   yes
  </sporty>
 </clothing>
 <clothing>
  <id>
   352949553
  </id>
  <name>
   Reebok Pants K-5511
  </name>
  <category>
   Pants
  </category>
  <size>
   XXL
  </size>
  <color>
   Желтый
  </color>
  <material>
   Полиэстер
  </material>
  <price>
   110055
  </price>
  <rating>
   1.03
  </rating>
  <reviews>
   950705
  </reviews>
  <exclusive>
   no
  </exclusive>
 </clothing>
 <clothing>
  <id>
   877144911
  </id>
  <name>
   Lacoste Sweater G-9679
  </name>
  <category>
   Sweater
  </category>
  <size>
   XXL
  </size>
  <color>
   Фиолетовый
  </color>
  <material>
   Шерсть
  </material>
  <price>
   172993
  </price>
  <rating>
   1.68
  </rating>
  <reviews>
   733487
  </reviews>
  <sporty>
   no
  </sporty>
 </clothing>
 <clothing>
  <id>
   204517036
  </id>
  <name>
   Adidas Gloves P-8536
  </name>
  <category>
   Gloves
  </category>
  <size>
   XXL
  </size>
  <color>
   Оранжевый
  </color>
  <material>
   Нейлон
  </material>
  <price>
   361381
  </price>
  <rating>
   1.85
  </rating>
  <reviews>
   113559
  </reviews>
  <new>
   +
  </new>
 </clothing>
 <clothing>
  <id>
   476743835
  </id>
  <name>
   Asics Gloves A-6945
  </name>
  <category>
   Gloves
  </category>
  <size>
   M
  </size>
  <color>
   Зеленый
  </color>
  <material>
   Шерсть
  </material>
  <price>
   274034
  </price>
  <rating>
   4.0
  </rating>
  <reviews>
   120567
  </reviews>
  <new>
   -
  </new>
 </clothing>
 <clothing>
  <id>
   288153076
  </id>
  <name>
   Adidas Sweater C-8330
  </name>
  <category>
   Sweater
  </category>
  <size>
   S
  </size>
  <color>
   Фиолетовый
  </color>
  <material>
   Вискоза
  </material>
  <price>
   964134
  </price>
  <rating>
   1.85
  </rating>
  <reviews>
   60502
  </reviews>
  <exclusive>
   no
  </exclusive>
 </clothing>
 <clothing>
  <id>
   362159662
  </id>
  <name>
   Fila Shoes V-3072
  </name>
  <category>
   Shoes
  </category>
  <size>
   M
  </size>
  <color>
   Синий
  </color>
  <material>
   Нейлон
  </material>
  <price>
   197684
  </price>
  <rating>
   1.84
  </rating>
  <reviews>
   391495
  </reviews>
  <new>
   -
  </new>
  <sporty>
   no
  </sporty>
 </clothing>
 <clothing>
  <id>
   876407914
  </id>
  <name>
   Brooks Sweater O-4909
  </name>
  <category>
   Sweater
  </category>
  <size>
   XL
  </size>
  <color>
   Зеленый
  </color>
  <material>
   Шерсть
  </material>
  <price>
   323619
  </price>
  <rating>
   4.45
  </rating>
  <reviews>
   684580
  </reviews>
  <new>
   -
  </new>
  <sporty>
   no
  </sporty>
 </clothing>
 <clothing>
  <id>
   913261956
  </id>
  <name>
   Under Armour Belts Y-5569
  </name>
  <category>
   Belts
  </category>
  <size>
   L
  </size>
  <color>
   Красный
  </color>
  <material>
   Кожа
  </material>
  <price>
   502422
  </price>
  <rating>
   1.2
  </rating>
  <reviews>
   651539
  </reviews>
  <exclusive>
   no
  </exclusive>
  <sporty>
   no
  </sporty>
 </clothing>
 <clothing>
  <id>
   429386342
  </id>
  <name>
   Fila Shirt D-3853
  </name>
  <category>
   Shirt
  </category>
  <size>
   M
  </size>
  <color>
   Красный
  </color>
  <material>
   Полиэстер
  </material>
  <price>
   722653
  </price>
  <rating>
   1.41
  </rating>
  <reviews>
   108902
  </reviews>
  <new>
   -
  </new>
 </clothing>
 <clothing>
  <id>
   402863708
  </id>
  <name>
   Ellesse Shoes Y-5185
  </name>
  <category>
   Shoes
  </category>
  <size>
   L
  </size>
  <color>
   Голубой
  </color>
  <material>
   Полиэстер
  </material>
  <price>
   130543
  </price>
  <rating>
   3.14
  </rating>
  <reviews>
   312657
  </reviews>
  <exclusive>
   no
  </exclusive>
  <sporty>
   no
  </sporty>
 </clothing>
 <clothing>
  <id>
   708674311
  </id>
  <name>
   Reebok Dress L-6040
  </name>
  <category>
   Dress
  </category>
  <size>
   XL
  </size>
  <color>
   Голубой
  </color>
  <material>
   Хлопок
  </material>
  <price>
   814330
  </price>
  <rating>
   2.12
  </rating>
  <reviews>
   136767
  </reviews>
  <new>
   -
  </new>
 </clothing>
 <clothing>
  <id>
   592185190
  </id>
  <name>
   Under Armour Umbrellas J-7905
  </name>
  <category>
   Umbrellas
  </category>
  <size>
   XL
  </size>
  <color>
   Желтый
  </color>
  <material>
   Шерсть
  </material>
  <price>
   500458
  </price>
  <rating>
   2.06
  </rating>
  <reviews>
   550768
  </reviews>
  <new>
   -
  </new>
  <sporty>
   yes
  </sporty>
 </clothing>
 <clothing>
  <id>
   234010959
  </id>
  <name>
   DC Handbags N-8728
  </name>
  <category>
   Handbags
  </category>
  <size>
   XXL
  </size>
  <color>
   Красный
  </color>
  <material>
   Лен
  </material>
  <price>
   446632
  </price>
  <rating>
   3.26
  </rating>
  <reviews>
   618233
  </reviews>
  <new>
   -
  </new>
  <exclusive>
   yes
  </exclusive>
  <sporty>
   no
  </sporty>
 </clothing>
 <clothing>
  <id>
   589099822
  </id>
  <name>
   Adidas Hat N-3322
  </name>
  <category>
   Hat
  </category>
  <size>
   S
  </size>
  <color>
   Фиолетовый
  </color>
  <material>
   Кожа
  </material>
  <price>
   209495
  </price>
  <rating>
   2.88
  </rating>
  <reviews>
   577907
  </reviews>
  <new>
   -
  </new>
  <exclusive>
   no
  </exclusive>
 </clothing>
 <clothing>
  <id>
   915055203
  </id>
  <name>
   PleinSport Sweater P-4508
  </name>
  <category>
   Sweater
  </category>
  <size>
   L
  </size>
  <color>
   Желтый
  </color>
  <material>
   Кожа
  </material>
  <price>
   477666
  </price>
  <rating>
   2.35
  </rating>
  <reviews>
   84666
  </reviews>
  <new>
   -
  </new>
  <exclusive>
   no
  </exclusive>
 </clothing>
</clothing-items>
